cli/__init__.py
cli/main.py
core/__init__.py
core/html.py
core/markdown.py
core/pdf.py
core/extractor/__init__.py
core/extractor/django_extractor.py
core/extractor/fastapi_extractor.py
core/extractor/flask_extractor.py
sample_app/__init__.py
sample_app/main.py
smartdoc_cli-0.1.5.dist-info/licenses/LICENSE
smartdoc_cli-0.1.5.dist-info/METADATA
smartdoc_cli-0.1.5.dist-info/WHEEL
smartdoc_cli-0.1.5.dist-info/entry_points.txt
smartdoc_cli-0.1.5.dist-info/top_level.txt
smartdoc_cli-0.1.5.dist-info/RECORD
