Metadata-Version: 2.4
Name: smartdoc-cli
Version: 0.1.5
Summary: SmartDoc: A tool to generate API documentation for FastAPI, Flask, and Django projects.
Author-email: Mohammad Safwan Athar <mohammadsafwanathar27@gmail.com>
License: MIT
License-File: LICENSE
Requires-Dist: click==8.1.7
Requires-Dist: fastapi
Requires-Dist: flask
Requires-Dist: django
Requires-Dist: markdown
Requires-Dist: weasyprint
Requires-Dist: xhtml2pdf
Dynamic: license-file
